amsterdam/__init__.py
amsterdam/amsterdam.py
amsterdam/config/kibana/export.json
amsterdam/config/logstash/logstash.conf
amsterdam/config/scirius/local_settings.py
amsterdam/config/suricata/suricata.yaml
amsterdam/config/suricata/threshold.config
amsterdam/docker/elasticsearch/Dockerfile
amsterdam/docker/kibana/Dockerfile
amsterdam/docker/scirius/Dockerfile
amsterdam/docker/scirius/stamus-packages.list
amsterdam/docker/scirius/django/scirius.json
amsterdam/docker/scirius/django/scirius.sh
amsterdam/docker/suricata/Dockerfile
amsterdam/docker/suricata/stamus-packages.list
amsterdam/docker/suricata/suri_reloader
amsterdam/docker/suricata/supervisor.d/suri_reloader.conf
amsterdam/docker/suricata/supervisor.d/suricata.conf
amsterdam/templates/docker-compose.yml.j2
amsterdam-0.4.data/scripts/amsterdam
amsterdam-0.4.dist-info/DESCRIPTION.rst
amsterdam-0.4.dist-info/METADATA
amsterdam-0.4.dist-info/RECORD
amsterdam-0.4.dist-info/WHEEL
amsterdam-0.4.dist-info/metadata.json
amsterdam-0.4.dist-info/top_level.txt
