Metadata-Version: 2.0
Name: amsterdam
Version: 0.4
Summary: Suricata, ELK, Scirius on Docker
Home-page: https://github.com/StamusNetworks/amsterdam
Author: Stamus Networks
Author-email: oss@stamus-networks.com
License: UNKNOWN
Platform: UNKNOWN
Classifier: Development Status :: 3 - Alpha
Classifier: Environment :: Console
Classifier: Intended Audience :: System Administrators
Classifier: License :: OSI Approved :: GNU General Public License v3 (GPLv3)
Classifier: Operating System :: POSIX
Classifier: Programming Language :: Python
Classifier: Topic :: Security
Requires: argparse
Provides: amsterdam
